{
	"configurations" : 
	[
		{
			"directories" : 
			[
				{
					"build" : ".",
					"childIndexes" : 
					[
						1,
						4
					],
					"hasInstallRule" : true,
					"minimumCMakeVersion" : 
					{
						"string" : "3.8"
					},
					"projectIndex" : 0,
					"source" : ".",
					"targetIndexes" : 
					[
						0
					]
				},
				{
					"build" : "googletest",
					"childIndexes" : 
					[
						2
					],
					"hasInstallRule" : true,
					"minimumCMakeVersion" : 
					{
						"string" : "2.8.12"
					},
					"parentIndex" : 0,
					"projectIndex" : 1,
					"source" : "googletest"
				},
				{
					"build" : "googletest/googlemock",
					"childIndexes" : 
					[
						3
					],
					"hasInstallRule" : true,
					"minimumCMakeVersion" : 
					{
						"string" : "2.8.12"
					},
					"parentIndex" : 1,
					"projectIndex" : 2,
					"source" : "googletest/googlemock",
					"targetIndexes" : 
					[
						2,
						3
					]
				},
				{
					"build" : "googletest/googletest",
					"hasInstallRule" : true,
					"minimumCMakeVersion" : 
					{
						"string" : "2.8.12"
					},
					"parentIndex" : 2,
					"projectIndex" : 3,
					"source" : "googletest/googletest",
					"targetIndexes" : 
					[
						4,
						5
					]
				},
				{
					"build" : "test",
					"minimumCMakeVersion" : 
					{
						"string" : "3.8"
					},
					"parentIndex" : 0,
					"projectIndex" : 0,
					"source" : "test",
					"targetIndexes" : 
					[
						1
					]
				}
			],
			"name" : "",
			"projects" : 
			[
				{
					"childIndexes" : 
					[
						1
					],
					"directoryIndexes" : 
					[
						0,
						4
					],
					"name" : "MealApp",
					"targetIndexes" : 
					[
						0,
						1
					]
				},
				{
					"childIndexes" : 
					[
						2
					],
					"directoryIndexes" : 
					[
						1
					],
					"name" : "googletest-distribution",
					"parentIndex" : 0
				},
				{
					"childIndexes" : 
					[
						3
					],
					"directoryIndexes" : 
					[
						2
					],
					"name" : "gmock",
					"parentIndex" : 1,
					"targetIndexes" : 
					[
						2,
						3
					]
				},
				{
					"directoryIndexes" : 
					[
						3
					],
					"name" : "gtest",
					"parentIndex" : 2,
					"targetIndexes" : 
					[
						4,
						5
					]
				}
			],
			"targets" : 
			[
				{
					"directoryIndex" : 0,
					"id" : "MealApp::@6890427a1f51a3e7e1df",
					"jsonFile" : "target-MealApp-e0101f2e489005e52a2c.json",
					"name" : "MealApp",
					"projectIndex" : 0
				},
				{
					"directoryIndex" : 4,
					"id" : "MyTests::@36f028580bb02cc8272a",
					"jsonFile" : "target-MyTests-7ce2189f9747e365177c.json",
					"name" : "MyTests",
					"projectIndex" : 0
				},
				{
					"directoryIndex" : 2,
					"id" : "gmock::@d68da25237a7ca2351af",
					"jsonFile" : "target-gmock-03154884d630290066ff.json",
					"name" : "gmock",
					"projectIndex" : 2
				},
				{
					"directoryIndex" : 2,
					"id" : "gmock_main::@d68da25237a7ca2351af",
					"jsonFile" : "target-gmock_main-5d6a0e5be73460dfb85f.json",
					"name" : "gmock_main",
					"projectIndex" : 2
				},
				{
					"directoryIndex" : 3,
					"id" : "gtest::@f95b5c00bd49b3b4698d",
					"jsonFile" : "target-gtest-a49c8e4f465fdce4b691.json",
					"name" : "gtest",
					"projectIndex" : 3
				},
				{
					"directoryIndex" : 3,
					"id" : "gtest_main::@f95b5c00bd49b3b4698d",
					"jsonFile" : "target-gtest_main-e36b4f4b6d638977292e.json",
					"name" : "gtest_main",
					"projectIndex" : 3
				}
			]
		}
	],
	"kind" : "codemodel",
	"paths" : 
	{
		"build" : "/mntpliki_mic/C++/MealApp/build",
		"source" : "/mntpliki_mic/C++/MealApp"
	},
	"version" : 
	{
		"major" : 2,
		"minor" : 0
	}
}
